<xml __jClassName="playlists" skuId="jdn-2022-all">
    <playlist data="playlist_0Games" position="-1" visibility-uid="0">
        <itemlist items-count="14" sorted-by="random" CLASS="FTUE" design="6">
            <allMapsWithSmallCover VAL="DiamondsSHI" CLASS="FTUE" />
            <allMapsWithSmallCover VAL="Chiwawa" CLASS="FTUE" />
            <allMapsWithSmallCover VAL="Burn" CLASS="FTUE" />
            <allMapsWithSmallCover VAL="CrazyKids" CLASS="FTUE" />
            <allMapsWithSmallCover VAL="BestSongEver" CLASS="FTUE" />
            <allMapsWithSmallCover VAL="BoysBoys" CLASS="FTUE" />
            <allMapsWithSmallCover VAL="Blame" CLASS="FTUE" />
            <allMapsWithSmallCover VAL="BlackWidow" CLASS="FTUE" />
            <allMapsWithSmallCover VAL="ILoveIt" CLASS="FTUE" />
            <allMapsWithSmallCover VAL="Happy" CLASS="FTUE" />
            <allMapsWithSmallCover VAL="SheWolfALT" CLASS="FTUE" />
            <allMapsWithSmallCover VAL="OnlyGirl" CLASS="FTUE" />
            <allMapsWithSmallCover VAL="DarkHorseMU" CLASS="FTUE" />
            <allMapsWithSmallCover VAL="1999" CLASS="FTUE" />
        </itemlist>
    </playlist>
    <playlist data="playlist_1JAN" position="0" visibility-uid="0">
        <itemlist items-count="14" sorted-by="ZZ" CLASS="NORMAL" design="0">
            <allMapsWithSmallCover VAL="Levitating" CLASS="NORMAL" />
            <allMapsWithSmallCover VAL="RockYouBody" CLASS="NORMAL" />
            <allMapsWithSmallCover VAL="Believer" CLASS="NORMAL" />
            <allMapsWithSmallCover VAL="China" CLASS="NORMAL" />
            <allMapsWithSmallCover VAL="MoodALT" CLASS="NORMAL" />
            <allMapsWithSmallCover VAL="Mood" CLASS="NORMAL" />
            <allMapsWithSmallCover VAL="TGIF" CLASS="NORMAL" />
            <allMapsWithSmallCover VAL="BlackMam" CLASS="NORMAL" />
            <allMapsWithSmallCover VAL="Boombayah" CLASS="NORMAL" />
            <allMapsWithSmallCover VAL="Happy" CLASS="NORMAL" />
            <allMapsWithSmallCover VAL="Buttons" CLASS="NORMAL" />
            <allMapsWithSmallCover VAL="FlashPose" CLASS="NORMAL" />
            <allMapsWithSmallCover VAL="FreedFromDeesire" CLASS="NORMAL" />
            <allMapsWithSmallCover VAL="Good4U" CLASS="NORMAL" />
        </itemlist>
    </playlist>
    <playlist data="playlist_danc6Cert" position="-9" visibility-uid="0">
        <itemlist items-count="14" sorted-by="alphabet" CLASS="NORMAL" design="0">
            <allMapsWithSmallCover VAL="4x4" CLASS="NORMAL" />
            <allMapsWithSmallCover VAL="AboutThatBass" CLASS="NORMAL" />
            <allMapsWithSmallCover VAL="BadRomanceALT" CLASS="NORMAL" />
            <allMapsWithSmallCover VAL="Bailando" CLASS="NORMAL" />
            <allMapsWithSmallCover VAL="BestSongEver" CLASS="NORMAL" />
            <allMapsWithSmallCover VAL="BuiltForThisALT" CLASS="NORMAL" />
            <allMapsWithSmallCover VAL="CrazyKids" CLASS="NORMAL" />
            <allMapsWithSmallCover VAL="DancengQueen" CLASS="NORMAL" />
            <allMapsWithSmallCover VAL="DancengQueenCMU" CLASS="NORMAL" />
            <allMapsWithSmallCover VAL="DarkHorseALT" CLASS="NORMAL" />
            <allMapsWithSmallCover VAL="DiamondsALT" CLASS="NORMAL" />
            <allMapsWithSmallCover VAL="EdgeOfGlory" CLASS="NORMAL" />
            <allMapsWithSmallCover VAL="Ghost" CLASS="NORMAL" />
            <allMapsWithSmallCover VAL="NeonLights" CLASS="NORMAL" />
        </itemlist>
    </playlist>
</xml>